py_near/__init__.py
py_near/account.py
py_near/constants.py
py_near/models.py
py_near/providers.py
py_near/py.typed
py_near/transactions.py
py_near/utils.py
py_near/dapps/__init__.py
py_near/dapps/core.py
py_near/dapps/fts.py
py_near/dapps/ft/__init__.py
py_near/dapps/ft/async_client.py
py_near/dapps/ft/exceptions.py
py_near/dapps/ft/models.py
py_near/dapps/keypom/__init__.py
py_near/dapps/keypom/async_client.py
py_near/dapps/keypom/exceptions.py
py_near/dapps/keypom/models.py
py_near/dapps/staking/__init__.py
py_near/dapps/staking/async_client.py
py_near/dapps/staking/exceptions.py
py_near/dapps/staking/models.py
py_near/exceptions/__init__.py
py_near/exceptions/exceptions.py
py_near/exceptions/provider.py
py_near_fork-0.1.1.dist-info/METADATA
py_near_fork-0.1.1.dist-info/WHEEL
py_near_fork-0.1.1.dist-info/licenses/LICENSE
py_near_fork-0.1.1.dist-info/RECORD
