Metadata-Version: 2.4
Name: py-near-fork
Version: 0.1.1
Summary: Pretty simple and fully asynchronous framework for working with NEAR blockchain
Project-URL: homepage, https://github.com/pvolnov/py-near
Project-URL: documentation, https://py-near.readthedocs.io/en/latest
Project-URL: repository, https://github.com/pvolnov/py-near
Project-URL: changelog, https://github.com/pvolnov/py-near/blob/main/CHANGELOG.md
Project-URL: funding, https://opencollective.com/py-near
Project-URL: twitter, https://twitter.com/p_volnov
Author-email: pvolnov <petr@herewallet.app>
License: Permission is hereby granted, free of charge, to any
License-File: LICENSE
Keywords: async,near,python
Classifier: License :: OSI Approved :: MIT License
Classifier: Operating System :: OS Independent
Classifier: Programming Language :: Python :: 3
Requires-Python: <3.12,>=3.8
Requires-Dist: base58<3.0.0,>=2.1.1
Requires-Dist: frozenlist<2.0.0,>=1.4.1
Requires-Dist: httpx==0.26.0
Requires-Dist: loguru<1.0.0,>=0.7.2
Requires-Dist: py-near-primitives==0.2.3
Requires-Dist: pydantic<3.0.0,>=2.6.2
Requires-Dist: pynacl<2.0.0,>=1.5.0
Requires-Dist: ruff>=0.9.10
